gjtheme/__init__.py
gjtheme/layout.html
gjtheme/searchbox.html
gjtheme/support.py
gjtheme/theme.conf
gjtheme/__pycache__/__init__.cpython-310.pyc
gjtheme/static/gjtheme.css_t
gjtheme/static/grant-jenks-logo.png
gjtheme-0.4.3.dist-info/LICENSE
gjtheme-0.4.3.dist-info/METADATA
gjtheme-0.4.3.dist-info/WHEEL
gjtheme-0.4.3.dist-info/entry_points.txt
gjtheme-0.4.3.dist-info/top_level.txt
gjtheme-0.4.3.dist-info/RECORD
