Metadata-Version: 2.1
Name: gjtheme
Version: 0.4.3
Summary: Sphinx GJ Theme
Home-page: http://www.grantjenks.com/docs/gjtheme/
Author: Grant Jenks
Author-email: contact@grantjenks.com
License: Apache 2.0
Classifier: Development Status :: 4 - Beta
Classifier: License :: OSI Approved :: Apache Software License
Classifier: Natural Language :: English
Classifier: Programming Language :: Python
License-File: LICENSE
Requires-Dist: Sphinx
